astrodown/__main__.py
astrodown/cli/__init__.py
astrodown/cli/check.py
astrodown/cli/init.py
astrodown/cli/install.py
astrodown/cli/new.py
astrodown/cli/utils.py
astrodown/commands.py
astrodown/constants.py
astrodown/quarto.py
astrodown/templates/__init__.py
astrodown/templates/basic/cookiecutter.json
astrodown/templates/basic/{{ cookiecutter.project_name }}/.env.example
astrodown/templates/basic/{{ cookiecutter.project_name }}/.gitignore
astrodown/templates/basic/{{ cookiecutter.project_name }}/.pre-commit-config.yaml
astrodown/templates/basic/{{ cookiecutter.project_name }}/README.md
astrodown/templates/basic/{{ cookiecutter.project_name }}/_astrodown.yml
astrodown/templates/basic/{{ cookiecutter.project_name }}/_quarto.yml
astrodown/templates/basic/{{ cookiecutter.project_name }}/analysis/first.qmd
astrodown/templates/basic/{{ cookiecutter.project_name }}/analysis/penguins.ipynb
astrodown/templates/basic/{{ cookiecutter.project_name }}/astro.config.mjs
astrodown/templates/basic/{{ cookiecutter.project_name }}/data/mtcars.qmd
astrodown/templates/basic/{{ cookiecutter.project_name }}/index.qmd
astrodown/templates/basic/{{ cookiecutter.project_name }}/package.json
astrodown/templates/basic/{{ cookiecutter.project_name }}/scripts/algolia.ts
astrodown/templates/basic/{{ cookiecutter.project_name }}/scripts/post-render.py
astrodown/templates/basic/{{ cookiecutter.project_name }}/src/components/BaseHead.astro
astrodown/templates/basic/{{ cookiecutter.project_name }}/src/components/Card.astro
astrodown/templates/basic/{{ cookiecutter.project_name }}/src/components/Network.astro
astrodown/templates/basic/{{ cookiecutter.project_name }}/src/components/SiteFooter.astro
astrodown/templates/basic/{{ cookiecutter.project_name }}/src/components/SiteHeader.astro
astrodown/templates/basic/{{ cookiecutter.project_name }}/src/components/analysis/Metadata.astro
astrodown/templates/basic/{{ cookiecutter.project_name }}/src/components/data/DataPreview.tsx
astrodown-0.1.16.dist-info/entry_points.txt
astrodown-0.1.16.dist-info/WHEEL
astrodown-0.1.16.dist-info/METADATA
astrodown-0.1.16.dist-info/RECORD
