Metadata-Version: 2.1
Name: astrodown
Version: 0.1.16
Summary: A framework for creating shareable data science websites
Author: Qiushi Yan
Author-email: qiushi.yann@gmail.com
Requires-Python: >=3.8,<4.0
Classifier: Programming Language :: Python :: 3
Classifier: Programming Language :: Python :: 3.10
Classifier: Programming Language :: Python :: 3.8
Classifier: Programming Language :: Python :: 3.9
Requires-Dist: PyYAML (>=6.0,<7.0)
Requires-Dist: cookiecutter (>=2.1.1,<3.0.0)
Requires-Dist: pyodide-http (>=0.2.0,<0.3.0)
Requires-Dist: typer[all] (>=0.7.0,<0.8.0)
